nonebot_plugin_kuma_san/__init__.py
nonebot_plugin_kuma_san/model.py
nonebot_plugin_kuma_san/services/__init__.py
nonebot_plugin_kuma_san/services/stage_service.py
nonebot_plugin_kuma_san/utils/__init__.py
nonebot_plugin_kuma_san/utils/api_parse.py
nonebot_plugin_kuma_san/utils/common.py
nonebot_plugin_kuma_san/utils/constants.py
nonebot_plugin_kuma_san/utils/translate.py
nonebot_plugin_kuma_san-1.1.0.dist-info/LICENSE
nonebot_plugin_kuma_san-1.1.0.dist-info/METADATA
nonebot_plugin_kuma_san-1.1.0.dist-info/WHEEL
nonebot_plugin_kuma_san-1.1.0.dist-info/top_level.txt
nonebot_plugin_kuma_san-1.1.0.dist-info/RECORD
