Metadata-Version: 2.1
Name: nonebot-plugin-kuma-san
Version: 1.1.0
Summary: 一个获取斯普拉遁3场地信息用的nonebot插件
Author-email: ReiiNoki <reiinoki@outlook.com>
Project-URL: Homepage, https://github.com/ReiiNoki/nonebot_plugin_kuma_san
Project-URL: Bug Tracker, https://github.com/ReiiNoki/nonebot_plugin_kuma_san/issues
Classifier: Programming Language :: Python :: 3
Classifier: License :: OSI Approved :: MIT License
Classifier: Operating System :: OS Independent
Requires-Python: >=3.8
License-File: LICENSE
Requires-Dist: nonebot2 (>=2.0.0rc2)
Requires-Dist: nonebot-adapter-onebot (>=2.1.1)
Requires-Dist: httpx (>=0.23.0)
